Workbook

Sheet Home
B3: *Upload BOE in Any AI Website or Extract Data Manually
B4: *Only Mentioned Required Details in Input Form Sheet Yellow Highlighted Cell
B6: *For AI - Prompt
B8: Role: Act as an expert data extractor and customs document analyst.
B10: Task: I have attached a Bill of Entry for a recent shipment. Please carefully review the document and extract the specific data points listed below. Provide the final output as a clean, structured table that I can directly copy and paste into Excel.
B12: Please extract the following fields into individual columns:
B14: 1. Material Name / Description
B16: 2. Quantity
B18: 3. Unit Cost
B20: 4. Total Cost
B22: 5. Individual Assess Value (per material)
B24: 6. BCD Rate (Basic Customs Duty)
... B60: Clean Numbers: Ensure numerical values are formatted cleanly so they are immediately calculable in Excel (e.g., avoid mixing text and numbers in the same cell).

Sheet Input Form
B2: IMPORT DUTY CALCULATION - INPUT FORM
B4: HEADER INPUTS
B5: Total Weight (Kg)
B6: Exchange Rate
B7: Invoice Value ($)
B8: Freight (₹)
B9: Insurance (%)
B10: Miscellaneous Charges
B13: DATA ENTRY TABLE - Enter material details below (Yellow columns are inputs)
B14: Material Name | C14: Unit Price ($) | D14: Quantity | E14: BCD Rate (%) | F14: Unit Cost Quotated | G14: Unit Cost Duty + GST | H14: Actual Cost Excluding GST
F15: =Calculation!O11 | G15: =Calculation!P11 | H15: =Calculation!Q11
F17: =Calculation!O13 | G17: =Calculation!P13 | H17: =Calculation!Q13
F18: =Calculation!O14 | G18: =Calculation!P14 | H18: =Calculation!Q14
F19: =Calculation!O15 | G19: =Calculation!P15 | H19: =Calculation!Q15
F20: =Calculation!O16 | G20: =Calculation!P16 | H20: =Calculation!Q16
F21: =Calculation!O17 | G21: =Calculation!P17 | H21: =Calculation!Q17
F22: =Calculation!O18 | G22: =Calculation!P18 | H22: =Calculation!Q18
F23: =Calculation!O19 | G23: =Calculation!P19 | H23: =Calculation!Q19
F24: =Calculation!O20 | G24: =Calculation!P20 | H24: =Calculation!Q20
F25: =Calculation!O21 | G25: =Calculation!P21 | H25: =Calculation!Q21
F26: =Calculation!O22 | G26: =Calculation!P22 | H26: =Calculation!Q22
F27: =Calculation!O23 | G27: =Calculation!P23 | H27: =Calculation!Q23
... F34: =Calculation!O30 | G34: =Calculation!P30 | H34: =Calculation!Q30

Sheet Calculation
B1: By Air
B2: Total Weight | C2: ='Input Form'!C5 -> 0 | D2: Kg | E2: =IF(C2=0,0,D5/C2) -> 0
B3: Exchange Rate | C3: ='Input Form'!C6 -> 0
B4: Invoice Value | C4: ='Input Form'!C7 -> 0 | D4: =C4*C3 -> 0
B5: Freight | C5: ='Input Form'!C8 -> 0 | D5: =C5 -> 0
B6: Insurance | C6: ='Input Form'!C9 -> 0 | D6: =(D4+D7)*C6 -> 0
B7: Miscelenous Charges | C7: ='Input Form'!C10 -> 0 | D7: =C7*C3 -> 0
B8: Assess Value | D8: =SUM(D4:D7) -> 0
Q9: SAP Price(1to 2% Higher By adding miscellanous Charges Of Agent Fees & Transport Cost)
A10: Sr.No. | B10: Material | C10: Unit Price | D10: Quantity | E10: Invoice Value | F10: Freight | G10: Insurance | H10: Miscellanous | I10: Assess Value | J10: BCD Rate | K10: BCD | L10: SWS | M10: IGST | N10: Total Duty | O10: Unit Cost Quotated | P10: Unit Cost With Duty | Q10: Unit Cost Actual To Company
A11: 1 | B11: =IF('Input Form'!B15="","",'Input Form'!B15) | C11: =IF('Input Form'!B15="","",'Input Form'!C15) | D11: =IF('Input Form'!B15="","",'Input Form'!D15) | E11: =IF('Input Form'!B15="","",C11*D11*$C$3) | F11: =IF('Input Form'!B15="","",IF($D$4=0,0,(E11/$D$4)*$D$5)) | G11: =IF('Input Form'!B15="","",(E11+H11)*$C$6) | H11: =IF('Input Form'!B15="","",IF($D$4=0,0,(E11/$D$4)*$D$7)) | I11: =IF('Input Form'!B15="","",E11+F11+G11+H11) | J11: =IF('Input Form'!B15="","",'Input Form'!E15) | K11: =IF('Input Form'!B15="","",I11*J11) | L11: =IF('Input Form'!B15="","",K11*10%) | M11: =IF('Input Form'!B15="","",(I11+K11+L11)*18%) | N11: =IF('Input Form'!B15="","",K11+L11+M11) | O11: =IF('Input Form'!B15="","",C11*$C$3) | P11: =IF('Input Form'!B15="","",IF(D11=0,0,(N11+I11)/D11)) | Q11: =IF('Input Form'!B15="","",IF(D11=0,0,(I11+K11+L11)/D11))
A12: =A11+1 -> 2 | B12: =IF('Input Form'!B16="","",'Input Form'!B16) | C12: =IF('Input Form'!B16="","",'Input Form'!C16) | D12: =IF('Input Form'!B16="","",'Input Form'!D16) | E12: =IF('Input Form'!B16="","",C12*D12*$C$3) | F12: =IF('Input Form'!B16="","",IF($D$4=0,0,(E12/$D$4)*$D$5)) | G12: =IF('Input Form'!B16="","",(E12+H12)*$C$6) | H12: =IF('Input Form'!B16="","",IF($D$4=0,0,(E12/$D$4)*$D$7)) | I12: =IF('Input Form'!B16="","",E12+F12+G12+H12) | J12: =IF('Input Form'!B16="","",'Input Form'!E16) | K12: =IF('Input Form'!B16="","",I12*J12) | L12: =IF('Input Form'!B16="","",K12*10%) | M12: =IF('Input Form'!B16="","",(I12+K12+L12)*18%) | N12: =IF('Input Form'!B16="","",K12+L12+M12) | O12: =IF('Input Form'!B16="","",C12*$C$3) | P12: =IF('Input Form'!B16="","",IF(D12=0,0,(N12+I12)/D12)) | Q12: =IF('Input Form'!B16="","",IF(D12=0,0,(I12+K12+L12)/D12))
A13: =A12+1 -> 3 | B13: =IF('Input Form'!B17="","",'Input Form'!B17) | C13: =IF('Input Form'!B17="","",'Input Form'!C17) | D13: =IF('Input Form'!B17="","",'Input Form'!D17) | E13: =IF('Input Form'!B17="","",C13*D13*$C$3) | F13: =IF('Input Form'!B17="","",IF($D$4=0,0,(E13/$D$4)*$D$5)) | G13: =IF('Input Form'!B17="","",(E13+H13)*$C$6) | H13: =IF('Input Form'!B17="","",IF($D$4=0,0,(E13/$D$4)*$D$7)) | I13: =IF('Input Form'!B17="","",E13+F13+G13+H13) | J13: =IF('Input Form'!B17="","",'Input Form'!E17) | K13: =IF('Input Form'!B17="","",I13*J13) | L13: =IF('Input Form'!B17="","",K13*10%) | M13: =IF('Input Form'!B17="","",(I13+K13+L13)*18%) | N13: =IF('Input Form'!B17="","",K13+L13+M13) | O13: =IF('Input Form'!B17="","",C13*$C$3) | P13: =IF('Input Form'!B17="","",IF(D13=0,0,(N13+I13)/D13)) | Q13: =IF('Input Form'!B17="","",IF(D13=0,0,(I13+K13+L13)/D13))
A14: =A13+1 -> 4 | B14: =IF('Input Form'!B18="","",'Input Form'!B18) | C14: =IF('Input Form'!B18="","",'Input Form'!C18) | D14: =IF('Input Form'!B18="","",'Input Form'!D18) | E14: =IF('Input Form'!B18="","",C14*D14*$C$3) | F14: =IF('Input Form'!B18="","",IF($D$4=0,0,(E14/$D$4)*$D$5)) | G14: =IF('Input Form'!B18="","",(E14+H14)*$C$6) | H14: =IF('Input Form'!B18="","",IF($D$4=0,0,(E14/$D$4)*$D$7)) | I14: =IF('Input Form'!B18="","",E14+F14+G14+H14) | J14: =IF('Input Form'!B18="","",'Input Form'!E18) | K14: =IF('Input Form'!B18="","",I14*J14) | L14: =IF('Input Form'!B18="","",K14*10%) | M14: =IF('Input Form'!B18="","",(I14+K14+L14)*18%) | N14: =IF('Input Form'!B18="","",K14+L14+M14) | O14: =IF('Input Form'!B18="","",C14*$C$3) | P14: =IF('Input Form'!B18="","",IF(D14=0,0,(N14+I14)/D14)) | Q14: =IF('Input Form'!B18="","",IF(D14=0,0,(I14+K14+L14)/D14))
A15: =A14+1 -> 5 | B15: =IF('Input Form'!B19="","",'Input Form'!B19) | C15: =IF('Input Form'!B19="","",'Input Form'!C19) | D15: =IF('Input Form'!B19="","",'Input Form'!D19) | E15: =IF('Input Form'!B19="","",C15*D15*$C$3) | F15: =IF('Input Form'!B19="","",IF($D$4=0,0,(E15/$D$4)*$D$5)) | G15: =IF('Input Form'!B19="","",(E15+H15)*$C$6) | H15: =IF('Input Form'!B19="","",IF($D$4=0,0,(E15/$D$4)*$D$7)) | I15: =IF('Input Form'!B19="","",E15+F15+G15+H15) | J15: =IF('Input Form'!B19="","",'Input Form'!E19) | K15: =IF('Input Form'!B19="","",I15*J15) | L15: =IF('Input Form'!B19="","",K15*10%) | M15: =IF('Input Form'!B19="","",(I15+K15+L15)*18%) | N15: =IF('Input Form'!B19="","",K15+L15+M15) | O15: =IF('Input Form'!B19="","",C15*$C$3) | P15: =IF('Input Form'!B19="","",IF(D15=0,0,(N15+I15)/D15)) | Q15: =IF('Input Form'!B19="","",IF(D15=0,0,(I15+K15+L15)/D15))
A16: =A15+1 -> 6 | B16: =IF('Input Form'!B20="","",'Input Form'!B20) | C16: =IF('Input Form'!B20="","",'Input Form'!C20) | D16: =IF('Input Form'!B20="","",'Input Form'!D20) | E16: =IF('Input Form'!B20="","",C16*D16*$C$3) | F16: =IF('Input Form'!B20="","",IF($D$4=0,0,(E16/$D$4)*$D$5)) | G16: =IF('Input Form'!B20="","",(E16+H16)*$C$6) | H16: =IF('Input Form'!B20="","",IF($D$4=0,0,(E16/$D$4)*$D$7)) | I16: =IF('Input Form'!B20="","",E16+F16+G16+H16) | J16: =IF('Input Form'!B20="","",'Input Form'!E20) | K16: =IF('Input Form'!B20="","",I16*J16) | L16: =IF('Input Form'!B20="","",K16*10%) | M16: =IF('Input Form'!B20="","",(I16+K16+L16)*18%) | N16: =IF('Input Form'!B20="","",K16+L16+M16) | O16: =IF('Input Form'!B20="","",C16*$C$3) | P16: =IF('Input Form'!B20="","",IF(D16=0,0,(N16+I16)/D16)) | Q16: =IF('Input Form'!B20="","",IF(D16=0,0,(I16+K16+L16)/D16))
A17: =A16+1 -> 7 | B17: =IF('Input Form'!B21="","",'Input Form'!B21) | C17: =IF('Input Form'!B21="","",'Input Form'!C21) | D17: =IF('Input Form'!B21="","",'Input Form'!D21) | E17: =IF('Input Form'!B21="","",C17*D17*$C$3) | F17: =IF('Input Form'!B21="","",IF($D$4=0,0,(E17/$D$4)*$D$5)) | G17: =IF('Input Form'!B21="","",(E17+H17)*$C$6) | H17: =IF('Input Form'!B21="","",IF($D$4=0,0,(E17/$D$4)*$D$7)) | I17: =IF('Input Form'!B21="","",E17+F17+G17+H17) | J17: =IF('Input Form'!B21="","",'Input Form'!E21) | K17: =IF('Input Form'!B21="","",I17*J17) | L17: =IF('Input Form'!B21="","",K17*10%) | M17: =IF('Input Form'!B21="","",(I17+K17+L17)*18%) | N17: =IF('Input Form'!B21="","",K17+L17+M17) | O17: =IF('Input Form'!B21="","",C17*$C$3) | P17: =IF('Input Form'!B21="","",IF(D17=0,0,(N17+I17)/D17)) | Q17: =IF('Input Form'!B21="","",IF(D17=0,0,(I17+K17+L17)/D17))
A18: =A17+1 -> 8 | B18: =IF('Input Form'!B22="","",'Input Form'!B22) | C18: =IF('Input Form'!B22="","",'Input Form'!C22) | D18: =IF('Input Form'!B22="","",'Input Form'!D22) | E18: =IF('Input Form'!B22="","",C18*D18*$C$3) | F18: =IF('Input Form'!B22="","",IF($D$4=0,0,(E18/$D$4)*$D$5)) | G18: =IF('Input Form'!B22="","",(E18+H18)*$C$6) | H18: =IF('Input Form'!B22="","",IF($D$4=0,0,(E18/$D$4)*$D$7)) | I18: =IF('Input Form'!B22="","",E18+F18+G18+H18) | J18: =IF('Input Form'!B22="","",'Input Form'!E22) | K18: =IF('Input Form'!B22="","",I18*J18) | L18: =IF('Input Form'!B22="","",K18*10%) | M18: =IF('Input Form'!B22="","",(I18+K18+L18)*18%) | N18: =IF('Input Form'!B22="","",K18+L18+M18) | O18: =IF('Input Form'!B22="","",C18*$C$3) | P18: =IF('Input Form'!B22="","",IF(D18=0,0,(N18+I18)/D18)) | Q18: =IF('Input Form'!B22="","",IF(D18=0,0,(I18+K18+L18)/D18))
A19: =A18+1 -> 9 | B19: =IF('Input Form'!B23="","",'Input Form'!B23) | C19: =IF('Input Form'!B23="","",'Input Form'!C23) | D19: =IF('Input Form'!B23="","",'Input Form'!D23) | E19: =IF('Input Form'!B23="","",C19*D19*$C$3) | F19: =IF('Input Form'!B23="","",IF($D$4=0,0,(E19/$D$4)*$D$5)) | G19: =IF('Input Form'!B23="","",(E19+H19)*$C$6) | H19: =IF('Input Form'!B23="","",IF($D$4=0,0,(E19/$D$4)*$D$7)) | I19: =IF('Input Form'!B23="","",E19+F19+G19+H19) | J19: =IF('Input Form'!B23="","",'Input Form'!E23) | K19: =IF('Input Form'!B23="","",I19*J19) | L19: =IF('Input Form'!B23="","",K19*10%) | M19: =IF('Input Form'!B23="","",(I19+K19+L19)*18%) | N19: =IF('Input Form'!B23="","",K19+L19+M19) | O19: =IF('Input Form'!B23="","",C19*$C$3) | P19: =IF('Input Form'!B23="","",IF(D19=0,0,(N19+I19)/D19)) | Q19: =IF('Input Form'!B23="","",IF(D19=0,0,(I19+K19+L19)/D19))
A20: =A19+1 -> 10 | B20: =IF('Input Form'!B24="","",'Input Form'!B24) | C20: =IF('Input Form'!B24="","",'Input Form'!C24) | D20: =IF('Input Form'!B24="","",'Input Form'!D24) | E20: =IF('Input Form'!B24="","",C20*D20*$C$3) | F20: =IF('Input Form'!B24="","",IF($D$4=0,0,(E20/$D$4)*$D$5)) | G20: =IF('Input Form'!B24="","",(E20+H20)*$C$6) | H20: =IF('Input Form'!B24="","",IF($D$4=0,0,(E20/$D$4)*$D$7)) | I20: =IF('Input Form'!B24="","",E20+F20+G20+H20) | J20: =IF('Input Form'!B24="","",'Input Form'!E24) | K20: =IF('Input Form'!B24="","",I20*J20) | L20: =IF('Input Form'!B24="","",K20*10%) | M20: =IF('Input Form'!B24="","",(I20+K20+L20)*18%) | N20: =IF('Input Form'!B24="","",K20+L20+M20) | O20: =IF('Input Form'!B24="","",C20*$C$3) | P20: =IF('Input Form'!B24="","",IF(D20=0,0,(N20+I20)/D20)) | Q20: =IF('Input Form'!B24="","",IF(D20=0,0,(I20+K20+L20)/D20))
A21: =A20+1 -> 11 | B21: =IF('Input Form'!B25="","",'Input Form'!B25) | C21: =IF('Input Form'!B25="","",'Input Form'!C25) | D21: =IF('Input Form'!B25="","",'Input Form'!D25) | E21: =IF('Input Form'!B25="","",C21*D21*$C$3) | F21: =IF('Input Form'!B25="","",IF($D$4=0,0,(E21/$D$4)*$D$5)) | G21: =IF('Input Form'!B25="","",(E21+H21)*$C$6) | H21: =IF('Input Form'!B25="","",IF($D$4=0,0,(E21/$D$4)*$D$7)) | I21: =IF('Input Form'!B25="","",E21+F21+G21+H21) | J21: =IF('Input Form'!B25="","",'Input Form'!E25) | K21: =IF('Input Form'!B25="","",I21*J21) | L21: =IF('Input Form'!B25="","",K21*10%) | M21: =IF('Input Form'!B25="","",(I21+K21+L21)*18%) | N21: =IF('Input Form'!B25="","",K21+L21+M21) | O21: =IF('Input Form'!B25="","",C21*$C$3) | P21: =IF('Input Form'!B25="","",IF(D21=0,0,(N21+I21)/D21)) | Q21: =IF('Input Form'!B25="","",IF(D21=0,0,(I21+K21+L21)/D21))
A22: =A21+1 -> 12 | B22: =IF('Input Form'!B26="","",'Input Form'!B26) | C22: =IF('Input Form'!B26="","",'Input Form'!C26) | D22: =IF('Input Form'!B26="","",'Input Form'!D26) | E22: =IF('Input Form'!B26="","",C22*D22*$C$3) | F22: =IF('Input Form'!B26="","",IF($D$4=0,0,(E22/$D$4)*$D$5)) | G22: =IF('Input Form'!B26="","",(E22+H22)*$C$6) | H22: =IF('Input Form'!B26="","",IF($D$4=0,0,(E22/$D$4)*$D$7)) | I22: =IF('Input Form'!B26="","",E22+F22+G22+H22) | J22: =IF('Input Form'!B26="","",'Input Form'!E26) | K22: =IF('Input Form'!B26="","",I22*J22) | L22: =IF('Input Form'!B26="","",K22*10%) | M22: =IF('Input Form'!B26="","",(I22+K22+L22)*18%) | N22: =IF('Input Form'!B26="","",K22+L22+M22) | O22: =IF('Input Form'!B26="","",C22*$C$3) | P22: =IF('Input Form'!B26="","",IF(D22=0,0,(N22+I22)/D22)) | Q22: =IF('Input Form'!B26="","",IF(D22=0,0,(I22+K22+L22)/D22))
A23: =A22+1 -> 13 | B23: =IF('Input Form'!B27="","",'Input Form'!B27) | C23: =IF('Input Form'!B27="","",'Input Form'!C27) | D23: =IF('Input Form'!B27="","",'Input Form'!D27) | E23: =IF('Input Form'!B27="","",C23*D23*$C$3) | F23: =IF('Input Form'!B27="","",IF($D$4=0,0,(E23/$D$4)*$D$5)) | G23: =IF('Input Form'!B27="","",(E23+H23)*$C$6) | H23: =IF('Input Form'!B27="","",IF($D$4=0,0,(E23/$D$4)*$D$7)) | I23: =IF('Input Form'!B27="","",E23+F23+G23+H23) | J23: =IF('Input Form'!B27="","",'Input Form'!E27) | K23: =IF('Input Form'!B27="","",I23*J23) | L23: =IF('Input Form'!B27="","",K23*10%) | M23: =IF('Input Form'!B27="","",(I23+K23+L23)*18%) | N23: =IF('Input Form'!B27="","",K23+L23+M23) | O23: =IF('Input Form'!B27="","",C23*$C$3) | P23: =IF('Input Form'!B27="","",IF(D23=0,0,(N23+I23)/D23)) | Q23: =IF('Input Form'!B27="","",IF(D23=0,0,(I23+K23+L23)/D23))
... A30: =A29+1 -> 20 | B30: =IF('Input Form'!B34="","",'Input Form'!B34) | C30: =IF('Input Form'!B34="","",'Input Form'!C34) | D30: =IF('Input Form'!B34="","",'Input Form'!D34) | E30: =IF('Input Form'!B34="","",C30*D30*$C$3) | F30: =IF('Input Form'!B34="","",IF($D$4=0,0,(E30/$D$4)*$D$5)) | G30: =IF('Input Form'!B34="","",(E30+H30)*$C$6) | H30: =IF('Input Form'!B34="","",IF($D$4=0,0,(E30/$D$4)*$D$7)) | I30: =IF('Input Form'!B34="","",E30+F30+G30+H30) | J30: =IF('Input Form'!B34="","",'Input Form'!E34) | K30: =IF('Input Form'!B34="","",I30*J30) | L30: =IF('Input Form'!B34="","",K30*10%) | M30: =IF('Input Form'!B34="","",(I30+K30+L30)*18%) | N30: =IF('Input Form'!B34="","",K30+L30+M30) | O30: =IF('Input Form'!B34="","",C30*$C$3) | P30: =IF('Input Form'!B34="","",IF(D30=0,0,(N30+I30)/D30)) | Q30: =IF('Input Form'!B34="","",IF(D30=0,0,(I30+K30+L30)/D30))
